user_messages/__init__.py
user_messages/admin.py
user_messages/context_processors.py
user_messages/forms.py
user_messages/managers.py
user_messages/models.py
user_messages/signals.py
user_messages/urls.py
user_messages/utils.py
user_messages/views.py
user_messages/migrations/0001_initial.py
user_messages/migrations/0002_auto_20171107_1128.py
user_messages/migrations/0003_auto_20171108_1037.py
user_messages/migrations/0004_auto_20171108_1101.py
user_messages/migrations/__init__.py
user_messages/templatetags/__init__.py
user_messages/templatetags/user_messages_tags.py
user_messages/tests/__init__.py
user_messages/tests/manage.py
user_messages/tests/settings.py
user_messages/tests/test_forms.py
user_messages/tests/test_managers.py
user_messages/tests/test_models.py
user_messages/tests/test_views.py
user_messages/tests/templates/user_messages/inbox.html
user_messages/tests/templates/user_messages/message_create.html
user_messages/tests/templates/user_messages/thread_detail.html
geonode_user_messages-2.0.2.2.dist-info/METADATA
geonode_user_messages-2.0.2.2.dist-info/WHEEL
geonode_user_messages-2.0.2.2.dist-info/top_level.txt
geonode_user_messages-2.0.2.2.dist-info/RECORD
